{
  "$schema": "https://schema.tauri.app/config/2",
  "productName": "Jungle Bell",
  "version": "0.2.3-beta.1",
  "identifier": "dev.sijun-yang.jungle-bell",
  "build": {
    "frontendDist": "../src"
  },
  "app": {
    "withGlobalTauri": true,
    "windows": [],
    "security": {
      "csp": null
    }
  },
  "plugins": {
    "updater": {
      "pubkey": "dW50cnVzdGVkIGNvbW1lbnQ6IG1pbmlzaWduIHB1YmxpYyBrZXk6IEU0MjNFRDgwMjEwQzQ5OTkKUldTWlNRd2hnTzBqNUdLNkJvS3BrcmlranlzekJNd2dOOXl3Ty94Ykkrc0JBS0NkaTU2Wk5vRkwK",
      "endpoints": [
        "https://github.com/YangSiJun528/jungle-bell/releases/latest/download/latest.json"
      ]
    }
  },
  "bundle": {
    "active": true,
    "createUpdaterArtifacts": true,
    "targets": "all",
    "icon": [
      "icons/32x32.png",
      "icons/128x128.png",
      "icons/128x128@2x.png",
      "icons/icon.icns",
      "icons/icon.ico"
    ]
  }
}
